pseudonaja/__init__.py
pseudonaja/__main__.py
pseudonaja/debug.py
pseudonaja/c/PInterpreter.py
pseudonaja/c/PLexer.py
pseudonaja/c/PParser.py
pseudonaja/c/PSymbolTable.py
pseudonaja/c/__init__.py
pseudonaja/c/ast/__init__.py
pseudonaja/c/ast/binop.py
pseudonaja/c/ast/function.py
pseudonaja/c/ast/identifier.py
pseudonaja/c/ast/io.py
pseudonaja/c/ast/iteration.py
pseudonaja/c/ast/literal.py
pseudonaja/c/ast/misc.py
pseudonaja/c/ast/node.py
pseudonaja/c/ast/procedure.py
pseudonaja/c/ast/selection.py
pseudonaja/c/ast/statement_list.py
pseudonaja/c/ast/unop.py
pseudonaja-0.2.5.dist-info/AUTHORS.rst
pseudonaja-0.2.5.dist-info/LICENSE
pseudonaja-0.2.5.dist-info/METADATA
pseudonaja-0.2.5.dist-info/WHEEL
pseudonaja-0.2.5.dist-info/top_level.txt
pseudonaja-0.2.5.dist-info/RECORD
