Metadata-Version: 2.1
Name: pseudonaja
Version: 0.2.5
Summary: Pseudocode interpreter
Home-page: https://github.com/dsoon/pseudonaja
Author: David Soon
Author-email: david.soon@outlook.com
License: MIT license
Keywords: pseudonaja
Platform: UNKNOWN
Classifier: Development Status :: 2 - Pre-Alpha
Classifier: Intended Audience :: Developers
Classifier: License :: OSI Approved :: MIT License
Classifier: Natural Language :: English
Classifier: Programming Language :: Python :: 3.7
Requires-Python: >=3.7
Requires-Dist: sly (==0.4)
